ShiyanlouXinxianquanJiaochengHeji20160904Fix1/README.md
ShiyanlouXinxianquanJiaochengHeji20160904Fix1/__init__.py
ShiyanlouXinxianquanJiaochengHeji20160904Fix1/__main__.py
ShiyanlouXinxianquanJiaochengHeji20160904Fix1/file.epub
ShiyanlouXinxianquanJiaochengHeji20160904Fix1/index.html
ShiyanlouXinxianquanJiaochengHeji20160904Fix1/css/__init__.py
ShiyanlouXinxianquanJiaochengHeji20160904Fix1/css/annotations.css
ShiyanlouXinxianquanJiaochengHeji20160904Fix1/css/main.css
ShiyanlouXinxianquanJiaochengHeji20160904Fix1/css/normalize.css
ShiyanlouXinxianquanJiaochengHeji20160904Fix1/css/popup.css
ShiyanlouXinxianquanJiaochengHeji20160904Fix1/font/__init__.py
ShiyanlouXinxianquanJiaochengHeji20160904Fix1/font/fontello.eot
ShiyanlouXinxianquanJiaochengHeji20160904Fix1/font/fontello.svg
ShiyanlouXinxianquanJiaochengHeji20160904Fix1/font/fontello.ttf
ShiyanlouXinxianquanJiaochengHeji20160904Fix1/font/fontello.woff
ShiyanlouXinxianquanJiaochengHeji20160904Fix1/img/__init__.py
ShiyanlouXinxianquanJiaochengHeji20160904Fix1/img/annotator-glyph-sprite.png
ShiyanlouXinxianquanJiaochengHeji20160904Fix1/img/annotator-icon-sprite.png
ShiyanlouXinxianquanJiaochengHeji20160904Fix1/img/apple-touch-icon.png
ShiyanlouXinxianquanJiaochengHeji20160904Fix1/img/cancelfullscreen.png
ShiyanlouXinxianquanJiaochengHeji20160904Fix1/img/close.png
ShiyanlouXinxianquanJiaochengHeji20160904Fix1/img/fullscreen.png
ShiyanlouXinxianquanJiaochengHeji20160904Fix1/img/loader.gif
ShiyanlouXinxianquanJiaochengHeji20160904Fix1/img/menu-icon.png
ShiyanlouXinxianquanJiaochengHeji20160904Fix1/img/save.png
ShiyanlouXinxianquanJiaochengHeji20160904Fix1/img/saved.png
ShiyanlouXinxianquanJiaochengHeji20160904Fix1/img/settings-s.png
ShiyanlouXinxianquanJiaochengHeji20160904Fix1/img/settings.png
ShiyanlouXinxianquanJiaochengHeji20160904Fix1/img/star.png
ShiyanlouXinxianquanJiaochengHeji20160904Fix1/js/__init__.py
ShiyanlouXinxianquanJiaochengHeji20160904Fix1/js/epub.js
shiyanlou_xinxianquan_jiaocheng_heji_20160904_fix1-2024.3.2.0.dist-info/METADATA
shiyanlou_xinxianquan_jiaocheng_heji_20160904_fix1-2024.3.2.0.dist-info/WHEEL
shiyanlou_xinxianquan_jiaocheng_heji_20160904_fix1-2024.3.2.0.dist-info/entry_points.txt
shiyanlou_xinxianquan_jiaocheng_heji_20160904_fix1-2024.3.2.0.dist-info/top_level.txt
shiyanlou_xinxianquan_jiaocheng_heji_20160904_fix1-2024.3.2.0.dist-info/RECORD
